zpodcli/__init__.py
zpodcli/cmd/component_cli.py
zpodcli/cmd/endpoint_cli.py
zpodcli/cmd/endpoint_permission_cli.py
zpodcli/cmd/enet_cli.py
zpodcli/cmd/factory_cli.py
zpodcli/cmd/library_cli.py
zpodcli/cmd/permission_group_cli.py
zpodcli/cmd/permission_group_user_cli.py
zpodcli/cmd/profile_cli.py
zpodcli/cmd/setting_cli.py
zpodcli/cmd/user_cli.py
zpodcli/cmd/zpod_cli.py
zpodcli/cmd/zpod_component_cli.py
zpodcli/cmd/zpod_dns_cli.py
zpodcli/cmd/zpod_permission_cli.py
zpodcli/lib/factory_config.py
zpodcli/lib/file.py
zpodcli/lib/global_flags.py
zpodcli/lib/prompt.py
zpodcli/lib/utils.py
zpodcli/lib/zpod_client.py
zpodcli/main_cli.py
zpodcli-0.7.2.dist-info/METADATA
zpodcli-0.7.2.dist-info/WHEEL
zpodcli-0.7.2.dist-info/entry_points.txt
zpodcli-0.7.2.dist-info/RECORD
