Metadata-Version: 2.1
Name: zpodcli
Version: 0.7.2
Summary: 
License: MIT
Author: Timo Sugliani
Author-email: timo.sugliani@gmail.com
Requires-Python: >=3.10,<4.0
Classifier: License :: OSI Approved :: MIT License
Classifier: Programming Language :: Python :: 3
Classifier: Programming Language :: Python :: 3.10
Classifier: Programming Language :: Python :: 3.11
Requires-Dist: pydantic (==2.7.1)
Requires-Dist: pyyaml (>=6.0,<7.0)
Requires-Dist: typer (==0.12.3)
Requires-Dist: zpodsdk (==0.7.2)
